cedar/__init__.py
cedar/__init__.pyi
cedar/__main__.py
cedar/cedar.cpython-314-darwin.so
cedar/lean/README.md
cedar/lean/__init__.py
cedar/lean/analyze.py
cedar/lean/cli.py
cedar/lean/symcc.py
cedar/mcp.py
cedar/py.typed
cedar/schema/__init__.py
cedar/schema/types.py
cedar/schema/util.py
cedar_python-0.1.4.dist-info/METADATA
cedar_python-0.1.4.dist-info/WHEEL
cedar_python-0.1.4.dist-info/entry_points.txt
cedar_python-0.1.4.dist-info/licenses/LICENSE
cedar_python-0.1.4.dist-info/RECORD
