Metadata-Version: 2.4
Name: cedar-python
Version: 0.1.4
Classifier: Development Status :: 4 - Beta
Classifier: Intended Audience :: Developers
Classifier: License :: OSI Approved :: Apache Software License
Classifier: Operating System :: OS Independent
Classifier: Programming Language :: Python :: 3
Classifier: Programming Language :: Python :: 3.12
Classifier: Programming Language :: Python :: 3.13
Classifier: Programming Language :: Python :: 3.14
Classifier: Programming Language :: Rust
Classifier: Topic :: Security
Classifier: Topic :: Software Development :: Libraries :: Python Modules
Classifier: Typing :: Typed
Requires-Dist: click>=8.0,<9
Requires-Dist: pydantic>=2.4,<3
Requires-Dist: pydantic-settings>=2.0,<3
Requires-Dist: fastmcp>=2.0,<3 ; extra == 'mcp'
Provides-Extra: mcp
License-File: LICENSE
Summary: Python bindings for Cedar, the open-source policy language for access control.
Keywords: cedar,authorization,access-control,policy,security,iam
Author: Sondera
License: Apache-2.0
Requires-Python: >=3.12
Project-URL: Homepage, https://github.com/sondera-ai/cedar-python
Project-URL: Issues, https://github.com/sondera-ai/cedar-python/issues
Project-URL: Repository, https://github.com/sondera-ai/cedar-python
